azureml/__init__.py
azureml/train/__init__.py
azureml/train/_distributed_training.py
azureml/train/_estimator_helper.py
azureml/train/_script_validation.py
azureml/train/_telemetry_logger.py
azureml/train/sklearn.py
azureml/train/dnn/__init__.py
azureml/train/dnn/_chainer.py
azureml/train/dnn/_pytorch.py
azureml/train/dnn/_tensorflow.py
azureml/train/estimator/__init__.py
azureml/train/estimator/_estimator.py
azureml/train/estimator/_framework_base_estimator.py
azureml/train/estimator/_mml_base_estimator.py
azureml/train/estimator/scenarios/chainer-5.1.0-cpu.yml
azureml/train/estimator/scenarios/chainer-5.1.0-gpu.yml
azureml/train/estimator/scenarios/chainer-7.0.0-cpu.yml
azureml/train/estimator/scenarios/chainer-7.0.0-gpu.yml
azureml/train/estimator/scenarios/lightgbm-2.2.3-cpu.yml
azureml/train/estimator/scenarios/mockframework-1.0-cpu.yml
azureml/train/estimator/scenarios/mockframework-1.0-gpu.yml
azureml/train/estimator/scenarios/mockframework-1.1-cpu.yml
azureml/train/estimator/scenarios/mockframework-1.1-gpu.yml
azureml/train/estimator/scenarios/pytorch-1.0-cpu.yml
azureml/train/estimator/scenarios/pytorch-1.0-gpu.yml
azureml/train/estimator/scenarios/pytorch-1.1-cpu.yml
azureml/train/estimator/scenarios/pytorch-1.1-gpu.yml
azureml/train/estimator/scenarios/pytorch-1.2-cpu.yml
azureml/train/estimator/scenarios/pytorch-1.2-gpu.yml
azureml/train/estimator/scenarios/pytorch-1.3-cpu.yml
azureml/train/estimator/scenarios/pytorch-1.3-gpu.yml
azureml/train/estimator/scenarios/pytorch-1.4-cpu.yml
azureml/train/estimator/scenarios/pytorch-1.4-gpu.yml
azureml/train/estimator/scenarios/pytorch-1.5-cpu.yml
azureml/train/estimator/scenarios/pytorch-1.5-gpu.yml
azureml/train/estimator/scenarios/pytorch-1.6-cpu.yml
azureml/train/estimator/scenarios/pytorch-1.6-gpu.yml
azureml/train/estimator/scenarios/sklearn-0.20.3-cpu.yml
azureml/train/estimator/scenarios/tensorflow-1.10-cpu.yml
azureml/train/estimator/scenarios/tensorflow-1.10-gpu.yml
azureml_train_core-1.60.0.dist-info/licenses/LICENSE.txt
azureml_train_core-1.60.0.dist-info/METADATA
azureml_train_core-1.60.0.dist-info/WHEEL
azureml_train_core-1.60.0.dist-info/entry_points.txt
azureml_train_core-1.60.0.dist-info/top_level.txt
azureml_train_core-1.60.0.dist-info/RECORD
